cobra_log/__init__.py
cobra_log/_core.py
cobra_log/_log_levels.py
cobra_log/_utils.py
cobra_log/exceptions.py
cobra_log/types.py
cobra_log-1.0.0.dist-info/licenses/LICENSE
cobra_log-1.0.0.dist-info/METADATA
cobra_log-1.0.0.dist-info/WHEEL
cobra_log-1.0.0.dist-info/top_level.txt
cobra_log-1.0.0.dist-info/RECORD
