Metadata-Version: 2.4
Name: cobra-log
Version: 1.0.0
Summary: A lightweight and easy-to-use logging library for Python.
Author-email: Zhen Tian <zhen.tian.cs@gmail.com>
Project-URL: Homepage, https://github.com/tinchen777/cobra-log.git
Project-URL: Repository, https://github.com/tinchen777/cobra-log.git
Project-URL: Issues, https://github.com/tinchen777/cobra-log.git/issues
Classifier: Programming Language :: Python :: 3
Classifier: Programming Language :: Python :: 3.9
Classifier: Programming Language :: Python :: 3.10
Classifier: Programming Language :: Python :: 3.11
Classifier: Programming Language :: Python :: 3.12
Classifier: Programming Language :: Python :: 3.13
Classifier: Programming Language :: Python :: 3.14
Requires-Python: >=3.9
License-File: LICENSE
Dynamic: license-file
